cm_worker/__init__.py
cm_worker/worker.py
cm_worker-0.0.4.dist-info/LICENSE
cm_worker-0.0.4.dist-info/METADATA
cm_worker-0.0.4.dist-info/WHEEL
cm_worker-0.0.4.dist-info/top_level.txt
cm_worker-0.0.4.dist-info/RECORD
