Metadata-Version: 2.1
Name: cm_worker
Version: 0.0.4
Summary: CourseMapper Worker
Author-email: Jean Qussa <jean.qussa@stud.uni-due.de>
License: MIT License
Project-URL: Homepage, https://github.com/jeanqussa/cm-worker
Project-URL: Issues, https://github.com/jeanqussa/cm-worker/issues
Classifier: Programming Language :: Python :: 3
Classifier: License :: OSI Approved :: MIT License
Classifier: Operating System :: OS Independent
Requires-Python: >=3.7
License-File: LICENSE
Requires-Dist: redis
